[{"1":{"Kind":1}},{"1":{"Kind":2}},{"1":{"Kind":3}},{"1":{"Kind":4}},{"1":{"Kind":5}},{"1":{"Kind":6}},{"1":{"Kind":7}},{"1":{"Kind":8}},{"6":{"Value":"Microsoft.ElasticSan/elasticSans"}},{"6":{"Value":"2023-01-01"}},{"2":{"Name":"Microsoft.ElasticSan/elasticSans","Properties":{"id":{"Type":4,"Flags":10,"Description":"The resource id"},"name":{"Type":4,"Flags":9,"Description":"The resource name"},"type":{"Type":8,"Flags":10,"Description":"The resource type"},"apiVersion":{"Type":9,"Flags":10,"Description":"The resource api version"},"properties":{"Type":11,"Flags":1,"Description":"Properties of ElasticSan."},"tags":{"Type":62,"Flags":0,"Description":"Resource tags."},"location":{"Type":4,"Flags":1,"Description":"The geo-location where the resource lives"},"systemData":{"Type":47,"Flags":2,"Description":"Azure Resource Manager metadata containing createdBy and modifiedBy information."}}}},{"2":{"Name":"ElasticSanProperties","Properties":{"sku":{"Type":12,"Flags":1,"Description":"resource sku"},"availabilityZones":{"Type":18,"Flags":0,"Description":"Logical zone for Elastic San resource; example: [\"1\"]."},"provisioningState":{"Type":27,"Flags":2,"Description":"State of the operation on the resource."},"baseSizeTiB":{"Type":3,"Flags":1,"Description":"Base size of the Elastic San appliance in TiB."},"extendedCapacitySizeTiB":{"Type":3,"Flags":1,"Description":"Extended size of the Elastic San appliance in TiB."},"totalVolumeSizeGiB":{"Type":3,"Flags":2,"Description":"Total size of the provisioned Volumes in GiB."},"volumeGroupCount":{"Type":3,"Flags":2,"Description":"Total number of volume groups in this Elastic San appliance."},"totalIops":{"Type":3,"Flags":2,"Description":"Total Provisioned IOPS of the Elastic San appliance."},"totalMBps":{"Type":3,"Flags":2,"Description":"Total Provisioned MBps Elastic San appliance."},"totalSizeTiB":{"Type":3,"Flags":2,"Description":"Total size of the Elastic San appliance in TB."},"privateEndpointConnections":{"Type":58,"Flags":2,"Description":"The list of Private Endpoint Connections."},"publicNetworkAccess":{"Type":61,"Flags":0,"Description":"Allow or disallow public network access to ElasticSan. Value is optional but if passed in, must be 'Enabled' or 'Disabled'."}}}},{"2":{"Name":"Sku","Properties":{"name":{"Type":15,"Flags":1,"Description":"The sku name."},"tier":{"Type":17,"Flags":0,"Description":"The sku tier."}}}},{"6":{"Value":"Premium_LRS"}},{"6":{"Value":"Premium_ZRS"}},{"5":{"Elements":[13,14,4]}},{"6":{"Value":"Premium"}},{"5":{"Elements":[16,4]}},{"3":{"ItemType":4}},{"6":{"Value":"Invalid"}},{"6":{"Value":"Succeeded"}},{"6":{"Value":"Failed"}},{"6":{"Value":"Canceled"}},{"6":{"Value":"Pending"}},{"6":{"Value":"Creating"}},{"6":{"Value":"Updating"}},{"6":{"Value":"Deleting"}},{"5":{"Elements":[19,20,21,22,23,24,25,26,4]}},{"2":{"Name":"PrivateEndpointConnection","Properties":{"properties":{"Type":29,"Flags":1,"Description":"Private Endpoint Connection Properties."},"id":{"Type":4,"Flags":2,"Description":"Fully qualified resource ID for the resource. Ex - /subscriptions/{subscriptionId}/resourceGroups/{resourceGroupName}/providers/{resourceProviderNamespace}/{resourceType}/{resourceName}"},"name":{"Type":4,"Flags":2,"Description":"The name of the resource"},"type":{"Type":4,"Flags":2,"Description":"The type of the resource. E.g. \"Microsoft.Compute/virtualMachines\" or \"Microsoft.Storage/storageAccounts\""},"systemData":{"Type":47,"Flags":2,"Description":"Azure Resource Manager metadata containing createdBy and modifiedBy information."}}}},{"2":{"Name":"PrivateEndpointConnectionProperties","Properties":{"provisioningState":{"Type":38,"Flags":2,"Description":"Provisioning State of Private Endpoint connection resource"},"privateEndpoint":{"Type":39,"Flags":0,"Description":"Private Endpoint resource"},"privateLinkServiceConnectionState":{"Type":40,"Flags":1,"Description":"Private Link Service Connection State."},"groupIds":{"Type":46,"Flags":0,"Description":"List of resources private endpoint is mapped"}}}},{"6":{"Value":"Invalid"}},{"6":{"Value":"Succeeded"}},{"6":{"Value":"Failed"}},{"6":{"Value":"Canceled"}},{"6":{"Value":"Pending"}},{"6":{"Value":"Creating"}},{"6":{"Value":"Updating"}},{"6":{"Value":"Deleting"}},{"5":{"Elements":[30,31,32,33,34,35,36,37,4]}},{"2":{"Name":"PrivateEndpoint","Properties":{"id":{"Type":4,"Flags":2,"Description":"The ARM identifier for Private Endpoint"}}}},{"2":{"Name":"PrivateLinkServiceConnectionState","Properties":{"status":{"Type":45,"Flags":0,"Description":"Indicates whether the connection has been Approved/Rejected/Removed by the owner of the service."},"description":{"Type":4,"Flags":0,"Description":"The reason for approval/rejection of the connection."},"actionsRequired":{"Type":4,"Flags":0,"Description":"A message indicating if changes on the service provider require any updates on the consumer."}}}},{"6":{"Value":"Pending"}},{"6":{"Value":"Approved"}},{"6":{"Value":"Failed"}},{"6":{"Value":"Rejected"}},{"5":{"Elements":[41,42,43,44,4]}},{"3":{"ItemType":4}},{"2":{"Name":"SystemData","Properties":{"createdBy":{"Type":4,"Flags":0,"Description":"The identity that created the resource."},"createdByType":{"Type":52,"Flags":0,"Description":"The type of identity that created the resource."},"createdAt":{"Type":4,"Flags":0,"Description":"The timestamp of resource creation (UTC)."},"lastModifiedBy":{"Type":4,"Flags":0,"Description":"The identity that last modified the resource."},"lastModifiedByType":{"Type":57,"Flags":0,"Description":"The type of identity that last modified the resource."},"lastModifiedAt":{"Type":4,"Flags":0,"Description":"The timestamp of resource last modification (UTC)"}}}},{"6":{"Value":"User"}},{"6":{"Value":"Application"}},{"6":{"Value":"ManagedIdentity"}},{"6":{"Value":"Key"}},{"5":{"Elements":[48,49,50,51,4]}},{"6":{"Value":"User"}},{"6":{"Value":"Application"}},{"6":{"Value":"ManagedIdentity"}},{"6":{"Value":"Key"}},{"5":{"Elements":[53,54,55,56,4]}},{"3":{"ItemType":28}},{"6":{"Value":"Enabled"}},{"6":{"Value":"Disabled"}},{"5":{"Elements":[59,60,4]}},{"2":{"Name":"TrackedResourceTags","Properties":{},"AdditionalProperties":4}},{"4":{"Name":"Microsoft.ElasticSan/elasticSans@2023-01-01","ScopeType":8,"Body":10,"Flags":0}},{"6":{"Value":"Microsoft.ElasticSan/elasticSans/volumegroups"}},{"6":{"Value":"2023-01-01"}},{"2":{"Name":"Microsoft.ElasticSan/elasticSans/volumegroups","Properties":{"id":{"Type":4,"Flags":10,"Description":"The resource id"},"name":{"Type":4,"Flags":9,"Description":"The resource name"},"type":{"Type":64,"Flags":10,"Description":"The resource type"},"apiVersion":{"Type":65,"Flags":10,"Description":"The resource api version"},"identity":{"Type":67,"Flags":0,"Description":"The identity of the resource."},"properties":{"Type":74,"Flags":0,"Description":"Properties of VolumeGroup."},"systemData":{"Type":47,"Flags":2,"Description":"Azure Resource Manager metadata containing createdBy and modifiedBy information."}}}},{"2":{"Name":"Identity","Properties":{"principalId":{"Type":4,"Flags":2,"Description":"The principal ID of resource identity."},"tenantId":{"Type":4,"Flags":2,"Description":"The tenant ID of resource."},"type":{"Type":71,"Flags":1,"Description":"The identity type."},"userAssignedIdentities":{"Type":73,"Flags":0,"Description":"Gets or sets a list of key value pairs that describe the set of User Assigned identities that will be used with this volume group. The key is the ARM resource identifier of the identity."}}}},{"6":{"Value":"None"}},{"6":{"Value":"SystemAssigned"}},{"6":{"Value":"UserAssigned"}},{"5":{"Elements":[68,69,70,4]}},{"2":{"Name":"UserAssignedIdentity","Properties":{"principalId":{"Type":4,"Flags":2,"Description":"The principal ID of the identity."},"clientId":{"Type":4,"Flags":2,"Description":"The client ID of the identity."}}}},{"2":{"Name":"IdentityUserAssignedIdentities","Properties":{},"AdditionalProperties":72}},{"2":{"Name":"VolumeGroupProperties","Properties":{"provisioningState":{"Type":83,"Flags":2,"Description":"State of the operation on the resource."},"protocolType":{"Type":86,"Flags":0,"Description":"Type of storage target"},"encryption":{"Type":89,"Flags":0,"Description":"Type of encryption"},"encryptionProperties":{"Type":90,"Flags":0,"Description":"Encryption Properties describing Key Vault and Identity information"},"networkAcls":{"Type":93,"Flags":0,"Description":"A collection of rules governing the accessibility from specific network locations."},"privateEndpointConnections":{"Type":98,"Flags":2,"Description":"The list of Private Endpoint Connections."}}}},{"6":{"Value":"Invalid"}},{"6":{"Value":"Succeeded"}},{"6":{"Value":"Failed"}},{"6":{"Value":"Canceled"}},{"6":{"Value":"Pending"}},{"6":{"Value":"Creating"}},{"6":{"Value":"Updating"}},{"6":{"Value":"Deleting"}},{"5":{"Elements":[75,76,77,78,79,80,81,82,4]}},{"6":{"Value":"Iscsi"}},{"6":{"Value":"None"}},{"5":{"Elements":[84,85,4]}},{"6":{"Value":"EncryptionAtRestWithPlatformKey"}},{"6":{"Value":"EncryptionAtRestWithCustomerManagedKey"}},{"5":{"Elements":[87,88,4]}},{"2":{"Name":"EncryptionProperties","Properties":{"keyVaultProperties":{"Type":91,"Flags":0,"Description":"Properties provided by key vault."},"identity":{"Type":92,"Flags":0,"Description":"The identity to be used with service-side encryption at rest."}}}},{"2":{"Name":"KeyVaultProperties","Properties":{"keyName":{"Type":4,"Flags":0,"Description":"The name of KeyVault key."},"keyVersion":{"Type":4,"Flags":0,"Description":"The version of KeyVault key."},"keyVaultUri":{"Type":4,"Flags":0,"Description":"The Uri of KeyVault."},"currentVersionedKeyIdentifier":{"Type":4,"Flags":2,"Description":"The object identifier of the current versioned Key Vault Key in use."},"lastKeyRotationTimestamp":{"Type":4,"Flags":2,"Description":"Timestamp of last rotation of the Key Vault Key."},"currentVersionedKeyExpirationTimestamp":{"Type":4,"Flags":2,"Description":"This is a read only property that represents the expiration time of the current version of the customer managed key used for encryption."}}}},{"2":{"Name":"EncryptionIdentity","Properties":{"userAssignedIdentity":{"Type":4,"Flags":0,"Description":"Resource identifier of the UserAssigned identity to be associated with server-side encryption on the volume group."}}}},{"2":{"Name":"NetworkRuleSet","Properties":{"virtualNetworkRules":{"Type":97,"Flags":0,"Description":"The list of virtual network rules."}}}},{"2":{"Name":"VirtualNetworkRule","Properties":{"id":{"Type":4,"Flags":1,"Description":"Resource ID of a subnet, for example: /subscriptions/{subscriptionId}/resourceGroups/{groupName}/providers/Microsoft.Network/virtualNetworks/{vnetName}/subnets/{subnetName}."},"action":{"Type":96,"Flags":0,"Description":"The action of virtual network rule."}}}},{"6":{"Value":"Allow"}},{"5":{"Elements":[95,4]}},{"3":{"ItemType":94}},{"3":{"ItemType":28}},{"4":{"Name":"Microsoft.ElasticSan/elasticSans/volumegroups@2023-01-01","ScopeType":8,"Body":66,"Flags":0}},{"6":{"Value":"Microsoft.ElasticSan/elasticSans/volumegroups/volumes"}},{"6":{"Value":"2023-01-01"}},{"2":{"Name":"Microsoft.ElasticSan/elasticSans/volumegroups/volumes","Properties":{"id":{"Type":4,"Flags":10,"Description":"The resource id"},"name":{"Type":4,"Flags":9,"Description":"The resource name"},"type":{"Type":100,"Flags":10,"Description":"The resource type"},"apiVersion":{"Type":101,"Flags":10,"Description":"The resource api version"},"properties":{"Type":103,"Flags":1,"Description":"Properties of Volume."},"systemData":{"Type":47,"Flags":2,"Description":"Azure Resource Manager metadata containing createdBy and modifiedBy information."}}}},{"2":{"Name":"VolumeProperties","Properties":{"volumeId":{"Type":4,"Flags":2,"Description":"Unique Id of the volume in GUID format"},"creationData":{"Type":104,"Flags":0,"Description":"State of the operation on the resource."},"sizeGiB":{"Type":3,"Flags":1,"Description":"Volume size."},"storageTarget":{"Type":111,"Flags":2,"Description":"Storage target information"},"managedBy":{"Type":130,"Flags":0,"Description":"Parent resource information."},"provisioningState":{"Type":139,"Flags":2,"Description":"State of the operation on the resource."}}}},{"2":{"Name":"SourceCreationData","Properties":{"createSource":{"Type":110,"Flags":0,"Description":"This enumerates the possible sources of a volume creation."},"sourceId":{"Type":4,"Flags":0,"Description":"Fully qualified resource ID for the resource. E.g. \"/subscriptions/{subscriptionId}/resourceGroups/{resourceGroupName}/providers/{resourceProviderNamespace}/{resourceType}/{resourceName}\""}}}},{"6":{"Value":"None"}},{"6":{"Value":"VolumeSnapshot"}},{"6":{"Value":"DiskSnapshot"}},{"6":{"Value":"Disk"}},{"6":{"Value":"DiskRestorePoint"}},{"5":{"Elements":[105,106,107,108,109,4]}},{"2":{"Name":"IscsiTargetInfo","Properties":{"targetIqn":{"Type":4,"Flags":2,"Description":"iSCSI Target IQN (iSCSI Qualified Name); example: \"iqn.2005-03.org.iscsi:server\"."},"targetPortalHostname":{"Type":4,"Flags":2,"Description":"iSCSI Target Portal Host Name"},"targetPortalPort":{"Type":3,"Flags":2,"Description":"iSCSI Target Portal Port"},"provisioningState":{"Type":120,"Flags":2,"Description":"State of the operation on the resource."},"status":{"Type":129,"Flags":0,"Description":"Operational status of the iSCSI Target."}}}},{"6":{"Value":"Invalid"}},{"6":{"Value":"Succeeded"}},{"6":{"Value":"Failed"}},{"6":{"Value":"Canceled"}},{"6":{"Value":"Pending"}},{"6":{"Value":"Creating"}},{"6":{"Value":"Updating"}},{"6":{"Value":"Deleting"}},{"5":{"Elements":[112,113,114,115,116,117,118,119,4]}},{"6":{"Value":"Invalid"}},{"6":{"Value":"Unknown"}},{"6":{"Value":"Healthy"}},{"6":{"Value":"Unhealthy"}},{"6":{"Value":"Updating"}},{"6":{"Value":"Running"}},{"6":{"Value":"Stopped"}},{"6":{"Value":"Stopped (deallocated)"}},{"5":{"Elements":[121,122,123,124,125,126,127,128,4]}},{"2":{"Name":"ManagedByInfo","Properties":{"resourceId":{"Type":4,"Flags":0,"Description":"Resource ID of the resource managing the volume, this is a restricted field and can only be set for internal use."}}}},{"6":{"Value":"Invalid"}},{"6":{"Value":"Succeeded"}},{"6":{"Value":"Failed"}},{"6":{"Value":"Canceled"}},{"6":{"Value":"Pending"}},{"6":{"Value":"Creating"}},{"6":{"Value":"Updating"}},{"6":{"Value":"Deleting"}},{"5":{"Elements":[131,132,133,134,135,136,137,138,4]}},{"4":{"Name":"Microsoft.ElasticSan/elasticSans/volumegroups/volumes@2023-01-01","ScopeType":8,"Body":102,"Flags":0}},{"6":{"Value":"Microsoft.ElasticSan/elasticSans/privateEndpointConnections"}},{"6":{"Value":"2023-01-01"}},{"2":{"Name":"Microsoft.ElasticSan/elasticSans/privateEndpointConnections","Properties":{"id":{"Type":4,"Flags":10,"Description":"The resource id"},"name":{"Type":4,"Flags":9,"Description":"The resource name"},"type":{"Type":141,"Flags":10,"Description":"The resource type"},"apiVersion":{"Type":142,"Flags":10,"Description":"The resource api version"},"properties":{"Type":29,"Flags":1,"Description":"Private Endpoint Connection Properties."},"systemData":{"Type":47,"Flags":2,"Description":"Azure Resource Manager metadata containing createdBy and modifiedBy information."}}}},{"4":{"Name":"Microsoft.ElasticSan/elasticSans/privateEndpointConnections@2023-01-01","ScopeType":8,"Body":143,"Flags":0}},{"6":{"Value":"Microsoft.ElasticSan/elasticSans/volumegroups/snapshots"}},{"6":{"Value":"2023-01-01"}},{"2":{"Name":"Microsoft.ElasticSan/elasticSans/volumegroups/snapshots","Properties":{"id":{"Type":4,"Flags":10,"Description":"The resource id"},"name":{"Type":4,"Flags":9,"Description":"The resource name"},"type":{"Type":145,"Flags":10,"Description":"The resource type"},"apiVersion":{"Type":146,"Flags":10,"Description":"The resource api version"},"properties":{"Type":148,"Flags":1,"Description":"Properties of Volume Snapshot."},"systemData":{"Type":47,"Flags":2,"Description":"Azure Resource Manager metadata containing createdBy and modifiedBy information."}}}},{"2":{"Name":"SnapshotProperties","Properties":{"creationData":{"Type":149,"Flags":1,"Description":"Data used when creating a volume snapshot."},"provisioningState":{"Type":158,"Flags":2,"Description":"State of the operation on the resource."},"sourceVolumeSizeGiB":{"Type":3,"Flags":2,"Description":"Size of Source Volume"},"volumeName":{"Type":4,"Flags":2,"Description":"Source Volume Name of a snapshot"}}}},{"2":{"Name":"SnapshotCreationData","Properties":{"sourceId":{"Type":4,"Flags":1,"Description":"Fully qualified resource ID of the volume. E.g. \"/subscriptions/{subscriptionId}/resourceGroups/{resourceGroupName}/providers/Microsoft.ElasticSan/elasticSans/{elasticSanName}/volumegroups/{volumeGroupName}/volumes/{volumeName}\""}}}},{"6":{"Value":"Invalid"}},{"6":{"Value":"Succeeded"}},{"6":{"Value":"Failed"}},{"6":{"Value":"Canceled"}},{"6":{"Value":"Pending"}},{"6":{"Value":"Creating"}},{"6":{"Value":"Updating"}},{"6":{"Value":"Deleting"}},{"5":{"Elements":[150,151,152,153,154,155,156,157,4]}},{"4":{"Name":"Microsoft.ElasticSan/elasticSans/volumegroups/snapshots@2023-01-01","ScopeType":8,"Body":147,"Flags":0}}]