[
  {
    "$type": "StringType"
  },
  {
    "$type": "StringLiteralType",
    "value": "Microsoft.Logz/monitors"
  },
  {
    "$type": "StringLiteralType",
    "value": "2020-10-01-preview"
  },
  {
    "$type": "ObjectType",
    "name": "Microsoft.Logz/monitors",
    "properties": {
      "id": {
        "type": {
          "$ref": "#/0"
        },
        "flags": 10,
        "description": "The resource id"
      },
      "name": {
        "type": {
          "$ref": "#/0"
        },
        "flags": 9,
        "description": "The resource name"
      },
      "type": {
        "type": {
          "$ref": "#/1"
        },
        "flags": 10,
        "description": "The resource type"
      },
      "apiVersion": {
        "type": {
          "$ref": "#/2"
        },
        "flags": 10,
        "description": "The resource api version"
      },
      "systemData": {
        "type": {
          "$ref": "#/4"
        },
        "flags": 2,
        "description": "The system metadata relating to this resource"
      },
      "properties": {
        "type": {
          "$ref": "#/15"
        },
        "flags": 0,
        "description": "Properties specific to the monitor resource."
      },
      "identity": {
        "type": {
          "$ref": "#/42"
        },
        "flags": 0
      },
      "tags": {
        "type": {
          "$ref": "#/46"
        },
        "flags": 0,
        "description": "Dictionary of <string>"
      },
      "location": {
        "type": {
          "$ref": "#/0"
        },
        "flags": 1
      }
    }
  },
  {
    "$type": "ObjectType",
    "name": "SystemData",
    "properties": {
      "createdBy": {
        "type": {
          "$ref": "#/0"
        },
        "flags": 0,
        "description": "The identity that created the resource."
      },
      "createdByType": {
        "type": {
          "$ref": "#/9"
        },
        "flags": 0,
        "description": "The type of identity that created the resource."
      },
      "createdAt": {
        "type": {
          "$ref": "#/0"
        },
        "flags": 0,
        "description": "The timestamp of resource creation (UTC)."
      },
      "lastModifiedBy": {
        "type": {
          "$ref": "#/0"
        },
        "flags": 0,
        "description": "The identity that last modified the resource."
      },
      "lastModifiedByType": {
        "type": {
          "$ref": "#/14"
        },
        "flags": 0,
        "description": "The type of identity that last modified the resource."
      },
      "lastModifiedAt": {
        "type": {
          "$ref": "#/0"
        },
        "flags": 0,
        "description": "The timestamp of resource last modification (UTC)"
      }
    }
  },
  {
    "$type": "StringLiteralType",
    "value": "User"
  },
  {
    "$type": "StringLiteralType",
    "value": "Application"
  },
  {
    "$type": "StringLiteralType",
    "value": "ManagedIdentity"
  },
  {
    "$type": "StringLiteralType",
    "value": "Key"
  },
  {
    "$type": "UnionType",
    "elements": [
      {
        "$ref": "#/5"
      },
      {
        "$ref": "#/6"
      },
      {
        "$ref": "#/7"
      },
      {
        "$ref": "#/8"
      },
      {
        "$ref": "#/0"
      }
    ]
  },
  {
    "$type": "StringLiteralType",
    "value": "User"
  },
  {
    "$type": "StringLiteralType",
    "value": "Application"
  },
  {
    "$type": "StringLiteralType",
    "value": "ManagedIdentity"
  },
  {
    "$type": "StringLiteralType",
    "value": "Key"
  },
  {
    "$type": "UnionType",
    "elements": [
      {
        "$ref": "#/10"
      },
      {
        "$ref": "#/11"
      },
      {
        "$ref": "#/12"
      },
      {
        "$ref": "#/13"
      },
      {
        "$ref": "#/0"
      }
    ]
  },
  {
    "$type": "ObjectType",
    "name": "MonitorProperties",
    "properties": {
      "provisioningState": {
        "type": {
          "$ref": "#/25"
        },
        "flags": 2,
        "description": "Flag specifying if the resource provisioning state as tracked by ARM."
      },
      "monitoringStatus": {
        "type": {
          "$ref": "#/28"
        },
        "flags": 0,
        "description": "Flag specifying if the resource monitoring is enabled or disabled."
      },
      "marketplaceSubscriptionStatus": {
        "type": {
          "$ref": "#/31"
        },
        "flags": 0,
        "description": "Flag specifying the Marketplace Subscription Status of the resource. If payment is not made in time, the resource will go in Suspended state."
      },
      "logzOrganizationProperties": {
        "type": {
          "$ref": "#/32"
        },
        "flags": 0
      },
      "userInfo": {
        "type": {
          "$ref": "#/33"
        },
        "flags": 0
      },
      "planData": {
        "type": {
          "$ref": "#/37"
        },
        "flags": 0
      },
      "liftrResourceCategory": {
        "type": {
          "$ref": "#/40"
        },
        "flags": 2
      },
      "liftrResourcePreference": {
        "type": {
          "$ref": "#/41"
        },
        "flags": 2,
        "description": "The priority of the resource."
      }
    }
  },
  {
    "$type": "StringLiteralType",
    "value": "Accepted"
  },
  {
    "$type": "StringLiteralType",
    "value": "Creating"
  },
  {
    "$type": "StringLiteralType",
    "value": "Updating"
  },
  {
    "$type": "StringLiteralType",
    "value": "Deleting"
  },
  {
    "$type": "StringLiteralType",
    "value": "Succeeded"
  },
  {
    "$type": "StringLiteralType",
    "value": "Failed"
  },
  {
    "$type": "StringLiteralType",
    "value": "Canceled"
  },
  {
    "$type": "StringLiteralType",
    "value": "Deleted"
  },
  {
    "$type": "StringLiteralType",
    "value": "NotSpecified"
  },
  {
    "$type": "UnionType",
    "elements": [
      {
        "$ref": "#/16"
      },
      {
        "$ref": "#/17"
      },
      {
        "$ref": "#/18"
      },
      {
        "$ref": "#/19"
      },
      {
        "$ref": "#/20"
      },
      {
        "$ref": "#/21"
      },
      {
        "$ref": "#/22"
      },
      {
        "$ref": "#/23"
      },
      {
        "$ref": "#/24"
      },
      {
        "$ref": "#/0"
      }
    ]
  },
  {
    "$type": "StringLiteralType",
    "value": "Enabled"
  },
  {
    "$type": "StringLiteralType",
    "value": "Disabled"
  },
  {
    "$type": "UnionType",
    "elements": [
      {
        "$ref": "#/26"
      },
      {
        "$ref": "#/27"
      },
      {
        "$ref": "#/0"
      }
    ]
  },
  {
    "$type": "StringLiteralType",
    "value": "Active"
  },
  {
    "$type": "StringLiteralType",
    "value": "Suspended"
  },
  {
    "$type": "UnionType",
    "elements": [
      {
        "$ref": "#/29"
      },
      {
        "$ref": "#/30"
      },
      {
        "$ref": "#/0"
      }
    ]
  },
  {
    "$type": "ObjectType",
    "name": "LogzOrganizationProperties",
    "properties": {
      "companyName": {
        "type": {
          "$ref": "#/0"
        },
        "flags": 0,
        "description": "Name of the Logz organization."
      },
      "id": {
        "type": {
          "$ref": "#/0"
        },
        "flags": 2,
        "description": "Id of the Logz organization."
      },
      "enterpriseAppId": {
        "type": {
          "$ref": "#/0"
        },
        "flags": 0,
        "description": "The Id of the Enterprise App used for Single sign on."
      },
      "singleSignOnUrl": {
        "type": {
          "$ref": "#/0"
        },
        "flags": 0,
        "description": "The login URL specific to this Logz Organization."
      }
    }
  },
  {
    "$type": "ObjectType",
    "name": "UserInfo",
    "properties": {
      "firstName": {
        "type": {
          "$ref": "#/34"
        },
        "flags": 0,
        "description": "First Name of the user"
      },
      "lastName": {
        "type": {
          "$ref": "#/34"
        },
        "flags": 0,
        "description": "Last Name of the user"
      },
      "emailAddress": {
        "type": {
          "$ref": "#/35"
        },
        "flags": 0,
        "description": "Email of the user used by Logz for contacting them if needed"
      },
      "phoneNumber": {
        "type": {
          "$ref": "#/36"
        },
        "flags": 0,
        "description": "Phone number of the user used by Logz for contacting them if needed"
      }
    }
  },
  {
    "$type": "StringType",
    "maxLength": 50
  },
  {
    "$type": "StringType",
    "pattern": "^[A-Za-z0-9._%+-]+@(?:[A-Za-z0-9-]+\\.)+[A-Za-z]{2,}$"
  },
  {
    "$type": "StringType",
    "maxLength": 40
  },
  {
    "$type": "ObjectType",
    "name": "PlanData",
    "properties": {
      "usageType": {
        "type": {
          "$ref": "#/34"
        },
        "flags": 0,
        "description": "different usage type like PAYG/COMMITTED. this could be enum"
      },
      "billingCycle": {
        "type": {
          "$ref": "#/34"
        },
        "flags": 0,
        "description": "different billing cycles like MONTHLY/WEEKLY. this could be enum"
      },
      "planDetails": {
        "type": {
          "$ref": "#/34"
        },
        "flags": 0,
        "description": "plan id as published by Logz"
      },
      "effectiveDate": {
        "type": {
          "$ref": "#/0"
        },
        "flags": 0,
        "description": "date when plan was applied"
      }
    }
  },
  {
    "$type": "StringLiteralType",
    "value": "Unknown"
  },
  {
    "$type": "StringLiteralType",
    "value": "MonitorLogs"
  },
  {
    "$type": "UnionType",
    "elements": [
      {
        "$ref": "#/38"
      },
      {
        "$ref": "#/39"
      },
      {
        "$ref": "#/0"
      }
    ]
  },
  {
    "$type": "IntegerType"
  },
  {
    "$type": "ObjectType",
    "name": "IdentityProperties",
    "properties": {
      "principalId": {
        "type": {
          "$ref": "#/0"
        },
        "flags": 2,
        "description": "The identity ID."
      },
      "tenantId": {
        "type": {
          "$ref": "#/0"
        },
        "flags": 2,
        "description": "The tenant ID of resource."
      },
      "type": {
        "type": {
          "$ref": "#/45"
        },
        "flags": 0
      }
    }
  },
  {
    "$type": "StringLiteralType",
    "value": "SystemAssigned"
  },
  {
    "$type": "StringLiteralType",
    "value": "UserAssigned"
  },
  {
    "$type": "UnionType",
    "elements": [
      {
        "$ref": "#/43"
      },
      {
        "$ref": "#/44"
      },
      {
        "$ref": "#/0"
      }
    ]
  },
  {
    "$type": "ObjectType",
    "name": "LogzMonitorResourceTags",
    "properties": {},
    "additionalProperties": {
      "$ref": "#/0"
    }
  },
  {
    "$type": "ResourceType",
    "name": "Microsoft.Logz/monitors@2020-10-01-preview",
    "scopeType": 8,
    "body": {
      "$ref": "#/3"
    },
    "flags": 0
  },
  {
    "$type": "StringLiteralType",
    "value": "Microsoft.Logz/monitors/tagRules"
  },
  {
    "$type": "StringLiteralType",
    "value": "2020-10-01-preview"
  },
  {
    "$type": "ObjectType",
    "name": "Microsoft.Logz/monitors/tagRules",
    "properties": {
      "id": {
        "type": {
          "$ref": "#/0"
        },
        "flags": 10,
        "description": "The resource id"
      },
      "name": {
        "type": {
          "$ref": "#/0"
        },
        "flags": 9,
        "description": "The resource name"
      },
      "type": {
        "type": {
          "$ref": "#/48"
        },
        "flags": 10,
        "description": "The resource type"
      },
      "apiVersion": {
        "type": {
          "$ref": "#/49"
        },
        "flags": 10,
        "description": "The resource api version"
      },
      "systemData": {
        "type": {
          "$ref": "#/4"
        },
        "flags": 2,
        "description": "The system metadata relating to this resource"
      },
      "properties": {
        "type": {
          "$ref": "#/51"
        },
        "flags": 0,
        "description": "Definition of the properties for a TagRules resource."
      }
    }
  },
  {
    "$type": "ObjectType",
    "name": "MonitoringTagRulesProperties",
    "properties": {
      "provisioningState": {
        "type": {
          "$ref": "#/61"
        },
        "flags": 2,
        "description": "Flag specifying if the resource provisioning state as tracked by ARM."
      },
      "logRules": {
        "type": {
          "$ref": "#/62"
        },
        "flags": 0,
        "description": "Set of rules for sending logs for the Monitor resource."
      },
      "systemData": {
        "type": {
          "$ref": "#/4"
        },
        "flags": 2,
        "description": "Metadata pertaining to creation and last modification of the resource."
      }
    }
  },
  {
    "$type": "StringLiteralType",
    "value": "Accepted"
  },
  {
    "$type": "StringLiteralType",
    "value": "Creating"
  },
  {
    "$type": "StringLiteralType",
    "value": "Updating"
  },
  {
    "$type": "StringLiteralType",
    "value": "Deleting"
  },
  {
    "$type": "StringLiteralType",
    "value": "Succeeded"
  },
  {
    "$type": "StringLiteralType",
    "value": "Failed"
  },
  {
    "$type": "StringLiteralType",
    "value": "Canceled"
  },
  {
    "$type": "StringLiteralType",
    "value": "Deleted"
  },
  {
    "$type": "StringLiteralType",
    "value": "NotSpecified"
  },
  {
    "$type": "UnionType",
    "elements": [
      {
        "$ref": "#/52"
      },
      {
        "$ref": "#/53"
      },
      {
        "$ref": "#/54"
      },
      {
        "$ref": "#/55"
      },
      {
        "$ref": "#/56"
      },
      {
        "$ref": "#/57"
      },
      {
        "$ref": "#/58"
      },
      {
        "$ref": "#/59"
      },
      {
        "$ref": "#/60"
      },
      {
        "$ref": "#/0"
      }
    ]
  },
  {
    "$type": "ObjectType",
    "name": "LogRules",
    "properties": {
      "sendAadLogs": {
        "type": {
          "$ref": "#/63"
        },
        "flags": 0,
        "description": "Flag specifying if AAD logs should be sent for the Monitor resource."
      },
      "sendSubscriptionLogs": {
        "type": {
          "$ref": "#/63"
        },
        "flags": 0,
        "description": "Flag specifying if subscription logs should be sent for the Monitor resource."
      },
      "sendActivityLogs": {
        "type": {
          "$ref": "#/63"
        },
        "flags": 0,
        "description": "Flag specifying if activity logs from Azure resources should be sent for the Monitor resource."
      },
      "filteringTags": {
        "type": {
          "$ref": "#/68"
        },
        "flags": 0,
        "description": "List of filtering tags to be used for capturing logs. This only takes effect if SendActivityLogs flag is enabled. If empty, all resources will be captured. If only Exclude action is specified, the rules will apply to the list of all available resources. If Include actions are specified, the rules will only include resources with the associated tags."
      }
    }
  },
  {
    "$type": "BooleanType"
  },
  {
    "$type": "ObjectType",
    "name": "FilteringTag",
    "properties": {
      "name": {
        "type": {
          "$ref": "#/0"
        },
        "flags": 0,
        "description": "The name (also known as the key) of the tag."
      },
      "value": {
        "type": {
          "$ref": "#/0"
        },
        "flags": 0,
        "description": "The value of the tag."
      },
      "action": {
        "type": {
          "$ref": "#/67"
        },
        "flags": 0,
        "description": "Valid actions for a filtering tag. Exclusion takes priority over inclusion."
      }
    }
  },
  {
    "$type": "StringLiteralType",
    "value": "Include"
  },
  {
    "$type": "StringLiteralType",
    "value": "Exclude"
  },
  {
    "$type": "UnionType",
    "elements": [
      {
        "$ref": "#/65"
      },
      {
        "$ref": "#/66"
      },
      {
        "$ref": "#/0"
      }
    ]
  },
  {
    "$type": "ArrayType",
    "itemType": {
      "$ref": "#/64"
    }
  },
  {
    "$type": "ResourceType",
    "name": "Microsoft.Logz/monitors/tagRules@2020-10-01-preview",
    "scopeType": 8,
    "body": {
      "$ref": "#/50"
    },
    "flags": 0
  },
  {
    "$type": "StringLiteralType",
    "value": "Microsoft.Logz/monitors/singleSignOnConfigurations"
  },
  {
    "$type": "StringLiteralType",
    "value": "2020-10-01-preview"
  },
  {
    "$type": "ObjectType",
    "name": "Microsoft.Logz/monitors/singleSignOnConfigurations",
    "properties": {
      "id": {
        "type": {
          "$ref": "#/0"
        },
        "flags": 10,
        "description": "The resource id"
      },
      "name": {
        "type": {
          "$ref": "#/0"
        },
        "flags": 9,
        "description": "The resource name"
      },
      "type": {
        "type": {
          "$ref": "#/70"
        },
        "flags": 10,
        "description": "The resource type"
      },
      "apiVersion": {
        "type": {
          "$ref": "#/71"
        },
        "flags": 10,
        "description": "The resource api version"
      },
      "systemData": {
        "type": {
          "$ref": "#/4"
        },
        "flags": 2,
        "description": "Metadata pertaining to creation and last modification of the resource."
      },
      "properties": {
        "type": {
          "$ref": "#/73"
        },
        "flags": 0
      }
    }
  },
  {
    "$type": "ObjectType",
    "name": "LogzSingleSignOnProperties",
    "properties": {
      "singleSignOnState": {
        "type": {
          "$ref": "#/78"
        },
        "flags": 0,
        "description": "Various states of the SSO resource"
      },
      "enterpriseAppId": {
        "type": {
          "$ref": "#/0"
        },
        "flags": 0,
        "description": "The Id of the Enterprise App used for Single sign-on."
      },
      "singleSignOnUrl": {
        "type": {
          "$ref": "#/0"
        },
        "flags": 0,
        "description": "The login URL specific to this Logz Organization."
      },
      "provisioningState": {
        "type": {
          "$ref": "#/88"
        },
        "flags": 2,
        "description": "Flag specifying if the resource provisioning state as tracked by ARM."
      }
    }
  },
  {
    "$type": "StringLiteralType",
    "value": "Initial"
  },
  {
    "$type": "StringLiteralType",
    "value": "Enable"
  },
  {
    "$type": "StringLiteralType",
    "value": "Disable"
  },
  {
    "$type": "StringLiteralType",
    "value": "Existing"
  },
  {
    "$type": "UnionType",
    "elements": [
      {
        "$ref": "#/74"
      },
      {
        "$ref": "#/75"
      },
      {
        "$ref": "#/76"
      },
      {
        "$ref": "#/77"
      },
      {
        "$ref": "#/0"
      }
    ]
  },
  {
    "$type": "StringLiteralType",
    "value": "Accepted"
  },
  {
    "$type": "StringLiteralType",
    "value": "Creating"
  },
  {
    "$type": "StringLiteralType",
    "value": "Updating"
  },
  {
    "$type": "StringLiteralType",
    "value": "Deleting"
  },
  {
    "$type": "StringLiteralType",
    "value": "Succeeded"
  },
  {
    "$type": "StringLiteralType",
    "value": "Failed"
  },
  {
    "$type": "StringLiteralType",
    "value": "Canceled"
  },
  {
    "$type": "StringLiteralType",
    "value": "Deleted"
  },
  {
    "$type": "StringLiteralType",
    "value": "NotSpecified"
  },
  {
    "$type": "UnionType",
    "elements": [
      {
        "$ref": "#/79"
      },
      {
        "$ref": "#/80"
      },
      {
        "$ref": "#/81"
      },
      {
        "$ref": "#/82"
      },
      {
        "$ref": "#/83"
      },
      {
        "$ref": "#/84"
      },
      {
        "$ref": "#/85"
      },
      {
        "$ref": "#/86"
      },
      {
        "$ref": "#/87"
      },
      {
        "$ref": "#/0"
      }
    ]
  },
  {
    "$type": "ResourceType",
    "name": "Microsoft.Logz/monitors/singleSignOnConfigurations@2020-10-01-preview",
    "scopeType": 8,
    "body": {
      "$ref": "#/72"
    },
    "flags": 0
  },
  {
    "$type": "StringLiteralType",
    "value": "Microsoft.Logz/monitors/accounts"
  },
  {
    "$type": "StringLiteralType",
    "value": "2020-10-01-preview"
  },
  {
    "$type": "ObjectType",
    "name": "Microsoft.Logz/monitors/accounts",
    "properties": {
      "id": {
        "type": {
          "$ref": "#/0"
        },
        "flags": 10,
        "description": "The resource id"
      },
      "name": {
        "type": {
          "$ref": "#/0"
        },
        "flags": 9,
        "description": "The resource name"
      },
      "type": {
        "type": {
          "$ref": "#/90"
        },
        "flags": 10,
        "description": "The resource type"
      },
      "apiVersion": {
        "type": {
          "$ref": "#/91"
        },
        "flags": 10,
        "description": "The resource api version"
      },
      "systemData": {
        "type": {
          "$ref": "#/4"
        },
        "flags": 2,
        "description": "The system metadata relating to this resource"
      },
      "properties": {
        "type": {
          "$ref": "#/15"
        },
        "flags": 0,
        "description": "Properties specific to the monitor resource."
      },
      "identity": {
        "type": {
          "$ref": "#/42"
        },
        "flags": 0
      },
      "tags": {
        "type": {
          "$ref": "#/93"
        },
        "flags": 0,
        "description": "Dictionary of <string>"
      },
      "location": {
        "type": {
          "$ref": "#/0"
        },
        "flags": 1
      }
    }
  },
  {
    "$type": "ObjectType",
    "name": "LogzMonitorResourceTags",
    "properties": {},
    "additionalProperties": {
      "$ref": "#/0"
    }
  },
  {
    "$type": "ResourceType",
    "name": "Microsoft.Logz/monitors/accounts@2020-10-01-preview",
    "scopeType": 8,
    "body": {
      "$ref": "#/92"
    },
    "flags": 0
  },
  {
    "$type": "StringLiteralType",
    "value": "Microsoft.Logz/monitors/accounts/tagRules"
  },
  {
    "$type": "StringLiteralType",
    "value": "2020-10-01-preview"
  },
  {
    "$type": "ObjectType",
    "name": "Microsoft.Logz/monitors/accounts/tagRules",
    "properties": {
      "id": {
        "type": {
          "$ref": "#/0"
        },
        "flags": 10,
        "description": "The resource id"
      },
      "name": {
        "type": {
          "$ref": "#/0"
        },
        "flags": 9,
        "description": "The resource name"
      },
      "type": {
        "type": {
          "$ref": "#/95"
        },
        "flags": 10,
        "description": "The resource type"
      },
      "apiVersion": {
        "type": {
          "$ref": "#/96"
        },
        "flags": 10,
        "description": "The resource api version"
      },
      "systemData": {
        "type": {
          "$ref": "#/4"
        },
        "flags": 2,
        "description": "The system metadata relating to this resource"
      },
      "properties": {
        "type": {
          "$ref": "#/51"
        },
        "flags": 0,
        "description": "Definition of the properties for a TagRules resource."
      }
    }
  },
  {
    "$type": "ResourceType",
    "name": "Microsoft.Logz/monitors/accounts/tagRules@2020-10-01-preview",
    "scopeType": 8,
    "body": {
      "$ref": "#/97"
    },
    "flags": 0
  },
  {
    "$type": "ObjectType",
    "name": "MonitoredResourceListResponse",
    "properties": {
      "value": {
        "type": {
          "$ref": "#/101"
        },
        "flags": 0,
        "description": "Results of a list operation."
      },
      "nextLink": {
        "type": {
          "$ref": "#/0"
        },
        "flags": 0,
        "description": "Link to the next set of results, if any."
      }
    }
  },
  {
    "$type": "ObjectType",
    "name": "MonitoredResource",
    "properties": {
      "id": {
        "type": {
          "$ref": "#/0"
        },
        "flags": 0,
        "description": "The ARM id of the resource."
      },
      "sendingMetrics": {
        "type": {
          "$ref": "#/63"
        },
        "flags": 0,
        "description": "Flag indicating if resource is sending metrics to Logz."
      },
      "reasonForMetricsStatus": {
        "type": {
          "$ref": "#/0"
        },
        "flags": 0,
        "description": "Reason for why the resource is sending metrics (or why it is not sending)."
      },
      "sendingLogs": {
        "type": {
          "$ref": "#/63"
        },
        "flags": 0,
        "description": "Flag indicating if resource is sending logs to Logz."
      },
      "systemData": {
        "type": {
          "$ref": "#/4"
        },
        "flags": 2,
        "description": "Metadata pertaining to creation and last modification of the resource."
      },
      "reasonForLogsStatus": {
        "type": {
          "$ref": "#/0"
        },
        "flags": 0,
        "description": "Reason for why the resource is sending logs (or why it is not sending)."
      }
    }
  },
  {
    "$type": "ArrayType",
    "itemType": {
      "$ref": "#/100"
    }
  },
  {
    "$type": "ResourceFunctionType",
    "name": "listMonitoredResources",
    "resourceType": "Microsoft.Logz/monitors",
    "apiVersion": "2020-10-01-preview",
    "output": {
      "$ref": "#/99"
    }
  },
  {
    "$type": "ObjectType",
    "name": "UserRoleRequest",
    "properties": {
      "emailAddress": {
        "type": {
          "$ref": "#/35"
        },
        "flags": 0,
        "description": "Email of the user used by Logz for contacting them if needed"
      }
    }
  },
  {
    "$type": "ObjectType",
    "name": "UserRoleListResponse",
    "properties": {
      "value": {
        "type": {
          "$ref": "#/110"
        },
        "flags": 0,
        "description": "List of user roles for Logz.io account."
      },
      "nextLink": {
        "type": {
          "$ref": "#/0"
        },
        "flags": 0,
        "description": "Link to the next set of results, if any."
      }
    }
  },
  {
    "$type": "ObjectType",
    "name": "UserRoleResponse",
    "properties": {
      "role": {
        "type": {
          "$ref": "#/109"
        },
        "flags": 0,
        "description": "User roles on configured in Logz.io account."
      }
    }
  },
  {
    "$type": "StringLiteralType",
    "value": "None"
  },
  {
    "$type": "StringLiteralType",
    "value": "User"
  },
  {
    "$type": "StringLiteralType",
    "value": "Admin"
  },
  {
    "$type": "UnionType",
    "elements": [
      {
        "$ref": "#/106"
      },
      {
        "$ref": "#/107"
      },
      {
        "$ref": "#/108"
      },
      {
        "$ref": "#/0"
      }
    ]
  },
  {
    "$type": "ArrayType",
    "itemType": {
      "$ref": "#/105"
    }
  },
  {
    "$type": "ResourceFunctionType",
    "name": "listUserRoles",
    "resourceType": "Microsoft.Logz/monitors",
    "apiVersion": "2020-10-01-preview",
    "output": {
      "$ref": "#/104"
    },
    "input": {
      "$ref": "#/103"
    }
  },
  {
    "$type": "ObjectType",
    "name": "VMExtensionPayload",
    "properties": {
      "apiKey": {
        "type": {
          "$ref": "#/113"
        },
        "flags": 0,
        "description": "API Key corresponding to the resource."
      },
      "region": {
        "type": {
          "$ref": "#/0"
        },
        "flags": 0,
        "description": "Logz.io region where the resource has been created."
      }
    }
  },
  {
    "$type": "StringType",
    "sensitive": true
  },
  {
    "$type": "ResourceFunctionType",
    "name": "vmHostPayload",
    "resourceType": "Microsoft.Logz/monitors",
    "apiVersion": "2020-10-01-preview",
    "output": {
      "$ref": "#/112"
    }
  },
  {
    "$type": "ObjectType",
    "name": "VMHostUpdateRequest",
    "properties": {
      "vmResourceIds": {
        "type": {
          "$ref": "#/117"
        },
        "flags": 0,
        "description": "Request of a list vm host update operation."
      },
      "state": {
        "type": {
          "$ref": "#/120"
        },
        "flags": 0,
        "description": "Specifies the state of the operation - install/ delete."
      }
    }
  },
  {
    "$type": "ObjectType",
    "name": "VMResources",
    "properties": {
      "id": {
        "type": {
          "$ref": "#/0"
        },
        "flags": 0,
        "description": "Request of a list vm host update operation."
      },
      "agentVersion": {
        "type": {
          "$ref": "#/0"
        },
        "flags": 0,
        "description": "Version of the Logz agent installed on the VM."
      }
    }
  },
  {
    "$type": "ArrayType",
    "itemType": {
      "$ref": "#/116"
    }
  },
  {
    "$type": "StringLiteralType",
    "value": "Install"
  },
  {
    "$type": "StringLiteralType",
    "value": "Delete"
  },
  {
    "$type": "UnionType",
    "elements": [
      {
        "$ref": "#/118"
      },
      {
        "$ref": "#/119"
      },
      {
        "$ref": "#/0"
      }
    ]
  },
  {
    "$type": "ObjectType",
    "name": "VMResourcesListResponse",
    "properties": {
      "value": {
        "type": {
          "$ref": "#/122"
        },
        "flags": 0,
        "description": "Response of a list vm host update operation."
      },
      "nextLink": {
        "type": {
          "$ref": "#/0"
        },
        "flags": 0,
        "description": "Link to the next set of results, if any."
      }
    }
  },
  {
    "$type": "ArrayType",
    "itemType": {
      "$ref": "#/116"
    }
  },
  {
    "$type": "ResourceFunctionType",
    "name": "vmHostUpdate",
    "resourceType": "Microsoft.Logz/monitors",
    "apiVersion": "2020-10-01-preview",
    "output": {
      "$ref": "#/121"
    },
    "input": {
      "$ref": "#/115"
    }
  },
  {
    "$type": "ResourceFunctionType",
    "name": "listVMHosts",
    "resourceType": "Microsoft.Logz/monitors",
    "apiVersion": "2020-10-01-preview",
    "output": {
      "$ref": "#/121"
    }
  },
  {
    "$type": "ResourceFunctionType",
    "name": "listMonitoredResources",
    "resourceType": "Microsoft.Logz/monitors/accounts",
    "apiVersion": "2020-10-01-preview",
    "output": {
      "$ref": "#/99"
    }
  },
  {
    "$type": "ResourceFunctionType",
    "name": "vmHostPayload",
    "resourceType": "Microsoft.Logz/monitors/accounts",
    "apiVersion": "2020-10-01-preview",
    "output": {
      "$ref": "#/112"
    }
  },
  {
    "$type": "ResourceFunctionType",
    "name": "vmHostUpdate",
    "resourceType": "Microsoft.Logz/monitors/accounts",
    "apiVersion": "2020-10-01-preview",
    "output": {
      "$ref": "#/121"
    },
    "input": {
      "$ref": "#/115"
    }
  },
  {
    "$type": "ResourceFunctionType",
    "name": "listVMHosts",
    "resourceType": "Microsoft.Logz/monitors/accounts",
    "apiVersion": "2020-10-01-preview",
    "output": {
      "$ref": "#/121"
    }
  }
]