[
  {
    "$type": "StringType",
    "minLength": 3,
    "maxLength": 98,
    "pattern": "^[a-zA-Z][a-zA-Z0-9-]{3,98}[a-zA-Z0-9]$"
  },
  {
    "$type": "StringLiteralType",
    "value": "Microsoft.Maps/accounts"
  },
  {
    "$type": "StringType"
  },
  {
    "$type": "StringLiteralType",
    "value": "2024-01-01-preview"
  },
  {
    "$type": "ObjectType",
    "name": "Microsoft.Maps/accounts",
    "properties": {
      "id": {
        "type": {
          "$ref": "#/2"
        },
        "flags": 10,
        "description": "The resource id"
      },
      "name": {
        "type": {
          "$ref": "#/0"
        },
        "flags": 9,
        "description": "The resource name"
      },
      "type": {
        "type": {
          "$ref": "#/1"
        },
        "flags": 10,
        "description": "The resource type"
      },
      "apiVersion": {
        "type": {
          "$ref": "#/3"
        },
        "flags": 10,
        "description": "The resource api version"
      },
      "sku": {
        "type": {
          "$ref": "#/5"
        },
        "flags": 1,
        "description": "The SKU of this account."
      },
      "kind": {
        "type": {
          "$ref": "#/9"
        },
        "flags": 0,
        "description": "Get or Set Kind property."
      },
      "identity": {
        "type": {
          "$ref": "#/10"
        },
        "flags": 0,
        "description": "Managed service identity (system assigned and/or user assigned identities)"
      },
      "properties": {
        "type": {
          "$ref": "#/19"
        },
        "flags": 0,
        "description": "The map account properties."
      },
      "tags": {
        "type": {
          "$ref": "#/68"
        },
        "flags": 0,
        "description": "Resource tags."
      },
      "location": {
        "type": {
          "$ref": "#/2"
        },
        "flags": 1,
        "description": "The geo-location where the resource lives"
      },
      "systemData": {
        "type": {
          "$ref": "#/51"
        },
        "flags": 2,
        "description": "Azure Resource Manager metadata containing createdBy and modifiedBy information."
      }
    }
  },
  {
    "$type": "ObjectType",
    "name": "Sku",
    "properties": {
      "name": {
        "type": {
          "$ref": "#/7"
        },
        "flags": 1,
        "description": "The name of the SKU, in standard format (such as G2)."
      },
      "tier": {
        "type": {
          "$ref": "#/2"
        },
        "flags": 2,
        "description": "Gets the sku tier. This is based on the SKU name."
      }
    }
  },
  {
    "$type": "StringLiteralType",
    "value": "G2"
  },
  {
    "$type": "UnionType",
    "elements": [
      {
        "$ref": "#/6"
      },
      {
        "$ref": "#/2"
      }
    ]
  },
  {
    "$type": "StringLiteralType",
    "value": "Gen2"
  },
  {
    "$type": "UnionType",
    "elements": [
      {
        "$ref": "#/8"
      },
      {
        "$ref": "#/2"
      }
    ]
  },
  {
    "$type": "ObjectType",
    "name": "ManagedServiceIdentity",
    "properties": {
      "principalId": {
        "type": {
          "$ref": "#/11"
        },
        "flags": 2,
        "description": "The service principal ID of the system assigned identity. This property will only be provided for a system assigned identity."
      },
      "tenantId": {
        "type": {
          "$ref": "#/11"
        },
        "flags": 2,
        "description": "The tenant ID of the system assigned identity. This property will only be provided for a system assigned identity."
      },
      "type": {
        "type": {
          "$ref": "#/16"
        },
        "flags": 1,
        "description": "Type of managed service identity (where both SystemAssigned and UserAssigned types are allowed)."
      },
      "userAssignedIdentities": {
        "type": {
          "$ref": "#/18"
        },
        "flags": 0,
        "description": "The set of user assigned identities associated with the resource. The userAssignedIdentities dictionary keys will be ARM resource ids in the form: '/subscriptions/{subscriptionId}/resourceGroups/{resourceGroupName}/providers/Microsoft.ManagedIdentity/userAssignedIdentities/{identityName}. The dictionary values can be empty objects ({}) in requests."
      }
    }
  },
  {
    "$type": "StringType",
    "minLength": 36,
    "maxLength": 36,
    "pattern": "^[0-9a-fA-F]{8}-([0-9a-fA-F]{4}-){3}[0-9a-fA-F]{12}$"
  },
  {
    "$type": "StringLiteralType",
    "value": "None"
  },
  {
    "$type": "StringLiteralType",
    "value": "SystemAssigned"
  },
  {
    "$type": "StringLiteralType",
    "value": "UserAssigned"
  },
  {
    "$type": "StringLiteralType",
    "value": "SystemAssigned,UserAssigned"
  },
  {
    "$type": "UnionType",
    "elements": [
      {
        "$ref": "#/12"
      },
      {
        "$ref": "#/13"
      },
      {
        "$ref": "#/14"
      },
      {
        "$ref": "#/15"
      },
      {
        "$ref": "#/2"
      }
    ]
  },
  {
    "$type": "ObjectType",
    "name": "UserAssignedIdentity",
    "properties": {
      "principalId": {
        "type": {
          "$ref": "#/11"
        },
        "flags": 2,
        "description": "The principal ID of the assigned identity."
      },
      "clientId": {
        "type": {
          "$ref": "#/11"
        },
        "flags": 2,
        "description": "The client ID of the assigned identity."
      }
    }
  },
  {
    "$type": "ObjectType",
    "name": "UserAssignedIdentities",
    "properties": {},
    "additionalProperties": {
      "$ref": "#/17"
    }
  },
  {
    "$type": "ObjectType",
    "name": "MapsAccountProperties",
    "properties": {
      "uniqueId": {
        "type": {
          "$ref": "#/2"
        },
        "flags": 2,
        "description": "A unique identifier for the Maps Account"
      },
      "disableLocalAuth": {
        "type": {
          "$ref": "#/20"
        },
        "flags": 0,
        "description": "Allows toggle functionality on Azure Policy to disable Azure Maps local authentication support. This will disable Shared Keys and Shared Access Signature Token authentication from any usage."
      },
      "provisioningState": {
        "type": {
          "$ref": "#/2"
        },
        "flags": 2,
        "description": "The provisioning state of the Maps account resource, Account updates can only be performed on terminal states. Terminal states: `Succeeded` and `Failed`"
      },
      "linkedResources": {
        "type": {
          "$ref": "#/22"
        },
        "flags": 0,
        "description": "The array of associated resources to the Maps account. Linked resource in the array cannot individually update, you must update all linked resources in the array together. These resources may be used on operations on the Azure Maps REST API. Access is controlled by the Maps Account Managed Identity(s) permissions to those resource(s)."
      },
      "cors": {
        "type": {
          "$ref": "#/23"
        },
        "flags": 0,
        "description": "Specifies CORS rules for the Blob service. You can include up to five CorsRule elements in the request. If no CorsRule elements are included in the request body, all CORS rules will be deleted, and CORS will be disabled for the Blob service."
      },
      "encryption": {
        "type": {
          "$ref": "#/27"
        },
        "flags": 0,
        "description": "All encryption configuration for a resource."
      },
      "privateEndpointConnections": {
        "type": {
          "$ref": "#/62"
        },
        "flags": 2,
        "description": "List of private endpoint connections associated with the Maps Account."
      },
      "publicNetworkAccess": {
        "type": {
          "$ref": "#/65"
        },
        "flags": 0,
        "description": "Property to specify whether the Maps Account will accept traffic from public internet. If set to 'disabled' all traffic except private endpoint traffic and that that originates from trusted services will be blocked."
      },
      "locations": {
        "type": {
          "$ref": "#/67"
        },
        "flags": 0,
        "description": "List of additional data processing regions for the Maps Account, which may result in requests being processed in another geography. Some features or results may be restricted to specific regions. By default, Maps REST APIs process requests according to the account location or the [geographic scope](https://learn.microsoft.com/en-us/azure/azure-maps/geographic-scope)."
      }
    }
  },
  {
    "$type": "BooleanType"
  },
  {
    "$type": "ObjectType",
    "name": "LinkedResource",
    "properties": {
      "uniqueName": {
        "type": {
          "$ref": "#/2"
        },
        "flags": 1,
        "description": "A provided name which uniquely identifies the linked resource."
      },
      "id": {
        "type": {
          "$ref": "#/2"
        },
        "flags": 1,
        "description": "ARM resource id in the form: '/subscriptions/{subscriptionId}/resourceGroups/{resourceGroupName}/providers/Microsoft.Storage/accounts/{storageName}'."
      }
    }
  },
  {
    "$type": "ArrayType",
    "itemType": {
      "$ref": "#/21"
    },
    "maxLength": 10
  },
  {
    "$type": "ObjectType",
    "name": "CorsRules",
    "properties": {
      "corsRules": {
        "type": {
          "$ref": "#/26"
        },
        "flags": 0,
        "description": "The list of CORS rules. You can include up to five CorsRule elements in the request."
      }
    }
  },
  {
    "$type": "ObjectType",
    "name": "CorsRule",
    "properties": {
      "allowedOrigins": {
        "type": {
          "$ref": "#/25"
        },
        "flags": 1,
        "description": "Required if CorsRule element is present. A list of origin domains that will be allowed via CORS, or \"*\" to allow all domains"
      }
    }
  },
  {
    "$type": "ArrayType",
    "itemType": {
      "$ref": "#/2"
    }
  },
  {
    "$type": "ArrayType",
    "itemType": {
      "$ref": "#/24"
    },
    "maxLength": 5
  },
  {
    "$type": "ObjectType",
    "name": "Encryption",
    "properties": {
      "infrastructureEncryption": {
        "type": {
          "$ref": "#/30"
        },
        "flags": 0,
        "description": "(Optional) Discouraged to include in resource definition. Only needed where it is possible to disable platform (AKA infrastructure) encryption. Azure SQL TDE is an example of this. Values are enabled and disabled."
      },
      "customerManagedKeyEncryption": {
        "type": {
          "$ref": "#/31"
        },
        "flags": 0,
        "description": "All Customer-managed key encryption properties for the resource."
      }
    }
  },
  {
    "$type": "StringLiteralType",
    "value": "enabled"
  },
  {
    "$type": "StringLiteralType",
    "value": "disabled"
  },
  {
    "$type": "UnionType",
    "elements": [
      {
        "$ref": "#/28"
      },
      {
        "$ref": "#/29"
      },
      {
        "$ref": "#/2"
      }
    ]
  },
  {
    "$type": "ObjectType",
    "name": "EncryptionCustomerManagedKeyEncryption",
    "properties": {
      "keyEncryptionKeyIdentity": {
        "type": {
          "$ref": "#/32"
        },
        "flags": 0,
        "description": "All identity configuration for Customer-managed key settings defining which identity should be used to auth to Key Vault."
      },
      "keyEncryptionKeyUrl": {
        "type": {
          "$ref": "#/2"
        },
        "flags": 0,
        "description": "key encryption key Url, versioned or unversioned. Ex: https://contosovault.vault.azure.net/keys/contosokek/562a4bb76b524a1493a6afe8e536ee78 or https://contosovault.vault.azure.net/keys/contosokek."
      }
    }
  },
  {
    "$type": "ObjectType",
    "name": "EncryptionCustomerManagedKeyEncryptionKeyIdentity",
    "properties": {
      "identityType": {
        "type": {
          "$ref": "#/36"
        },
        "flags": 0,
        "description": "The type of identity to use. Values can be systemAssignedIdentity, userAssignedIdentity, or delegatedResourceIdentity."
      },
      "userAssignedIdentityResourceId": {
        "type": {
          "$ref": "#/2"
        },
        "flags": 0,
        "description": "User assigned identity to use for accessing key encryption key Url. Ex: /subscriptions/fa5fc227-a624-475e-b696-cdd604c735bc/resourceGroups/<resource group>/providers/Microsoft.ManagedIdentity/userAssignedIdentities/myId. Mutually exclusive with identityType systemAssignedIdentity."
      },
      "federatedClientId": {
        "type": {
          "$ref": "#/11"
        },
        "flags": 0,
        "description": "application client identity to use for accessing key encryption key Url in a different tenant. Ex: f83c6b1b-4d34-47e4-bb34-9d83df58b540"
      },
      "delegatedIdentityClientId": {
        "type": {
          "$ref": "#/11"
        },
        "flags": 0,
        "description": "delegated identity to use for accessing key encryption key Url. Ex: /subscriptions/fa5fc227-a624-475e-b696-cdd604c735bc/resourceGroups/<resource group>/providers/Microsoft.ManagedIdentity/userAssignedIdentities/myId. Mutually exclusive with identityType systemAssignedIdentity and userAssignedIdentity - internal use only."
      }
    }
  },
  {
    "$type": "StringLiteralType",
    "value": "systemAssignedIdentity"
  },
  {
    "$type": "StringLiteralType",
    "value": "userAssignedIdentity"
  },
  {
    "$type": "StringLiteralType",
    "value": "delegatedResourceIdentity"
  },
  {
    "$type": "UnionType",
    "elements": [
      {
        "$ref": "#/33"
      },
      {
        "$ref": "#/34"
      },
      {
        "$ref": "#/35"
      },
      {
        "$ref": "#/2"
      }
    ]
  },
  {
    "$type": "ObjectType",
    "name": "PrivateEndpointConnection",
    "properties": {
      "properties": {
        "type": {
          "$ref": "#/38"
        },
        "flags": 0,
        "description": "Resource properties."
      },
      "id": {
        "type": {
          "$ref": "#/2"
        },
        "flags": 2,
        "description": "Fully qualified resource ID for the resource. E.g. \"/subscriptions/{subscriptionId}/resourceGroups/{resourceGroupName}/providers/{resourceProviderNamespace}/{resourceType}/{resourceName}\""
      },
      "name": {
        "type": {
          "$ref": "#/2"
        },
        "flags": 2,
        "description": "The name of the resource"
      },
      "type": {
        "type": {
          "$ref": "#/2"
        },
        "flags": 2,
        "description": "The type of the resource. E.g. \"Microsoft.Compute/virtualMachines\" or \"Microsoft.Storage/storageAccounts\""
      },
      "systemData": {
        "type": {
          "$ref": "#/51"
        },
        "flags": 2,
        "description": "Azure Resource Manager metadata containing createdBy and modifiedBy information."
      }
    }
  },
  {
    "$type": "ObjectType",
    "name": "PrivateEndpointConnectionProperties",
    "properties": {
      "groupIds": {
        "type": {
          "$ref": "#/39"
        },
        "flags": 2,
        "description": "The group ids for the private endpoint resource."
      },
      "privateEndpoint": {
        "type": {
          "$ref": "#/40"
        },
        "flags": 0,
        "description": "The private endpoint resource."
      },
      "privateLinkServiceConnectionState": {
        "type": {
          "$ref": "#/41"
        },
        "flags": 1,
        "description": "A collection of information about the state of the connection between service consumer and provider."
      },
      "provisioningState": {
        "type": {
          "$ref": "#/50"
        },
        "flags": 2,
        "description": "The provisioning state of the private endpoint connection resource."
      }
    }
  },
  {
    "$type": "ArrayType",
    "itemType": {
      "$ref": "#/2"
    }
  },
  {
    "$type": "ObjectType",
    "name": "PrivateEndpoint",
    "properties": {
      "id": {
        "type": {
          "$ref": "#/2"
        },
        "flags": 2,
        "description": "The ARM identifier for private endpoint."
      }
    }
  },
  {
    "$type": "ObjectType",
    "name": "PrivateLinkServiceConnectionState",
    "properties": {
      "status": {
        "type": {
          "$ref": "#/45"
        },
        "flags": 0,
        "description": "Indicates whether the connection has been Approved/Rejected/Removed by the owner of the service."
      },
      "description": {
        "type": {
          "$ref": "#/2"
        },
        "flags": 0,
        "description": "The reason for approval/rejection of the connection."
      },
      "actionsRequired": {
        "type": {
          "$ref": "#/2"
        },
        "flags": 0,
        "description": "A message indicating if changes on the service provider require any updates on the consumer."
      }
    }
  },
  {
    "$type": "StringLiteralType",
    "value": "Pending"
  },
  {
    "$type": "StringLiteralType",
    "value": "Approved"
  },
  {
    "$type": "StringLiteralType",
    "value": "Rejected"
  },
  {
    "$type": "UnionType",
    "elements": [
      {
        "$ref": "#/42"
      },
      {
        "$ref": "#/43"
      },
      {
        "$ref": "#/44"
      },
      {
        "$ref": "#/2"
      }
    ]
  },
  {
    "$type": "StringLiteralType",
    "value": "Succeeded"
  },
  {
    "$type": "StringLiteralType",
    "value": "Creating"
  },
  {
    "$type": "StringLiteralType",
    "value": "Deleting"
  },
  {
    "$type": "StringLiteralType",
    "value": "Failed"
  },
  {
    "$type": "UnionType",
    "elements": [
      {
        "$ref": "#/46"
      },
      {
        "$ref": "#/47"
      },
      {
        "$ref": "#/48"
      },
      {
        "$ref": "#/49"
      },
      {
        "$ref": "#/2"
      }
    ]
  },
  {
    "$type": "ObjectType",
    "name": "SystemData",
    "properties": {
      "createdBy": {
        "type": {
          "$ref": "#/2"
        },
        "flags": 0,
        "description": "The identity that created the resource."
      },
      "createdByType": {
        "type": {
          "$ref": "#/56"
        },
        "flags": 0,
        "description": "The type of identity that created the resource."
      },
      "createdAt": {
        "type": {
          "$ref": "#/2"
        },
        "flags": 0,
        "description": "The timestamp of resource creation (UTC)."
      },
      "lastModifiedBy": {
        "type": {
          "$ref": "#/2"
        },
        "flags": 0,
        "description": "The identity that last modified the resource."
      },
      "lastModifiedByType": {
        "type": {
          "$ref": "#/61"
        },
        "flags": 0,
        "description": "The type of identity that last modified the resource."
      },
      "lastModifiedAt": {
        "type": {
          "$ref": "#/2"
        },
        "flags": 0,
        "description": "The timestamp of resource last modification (UTC)"
      }
    }
  },
  {
    "$type": "StringLiteralType",
    "value": "User"
  },
  {
    "$type": "StringLiteralType",
    "value": "Application"
  },
  {
    "$type": "StringLiteralType",
    "value": "ManagedIdentity"
  },
  {
    "$type": "StringLiteralType",
    "value": "Key"
  },
  {
    "$type": "UnionType",
    "elements": [
      {
        "$ref": "#/52"
      },
      {
        "$ref": "#/53"
      },
      {
        "$ref": "#/54"
      },
      {
        "$ref": "#/55"
      },
      {
        "$ref": "#/2"
      }
    ]
  },
  {
    "$type": "StringLiteralType",
    "value": "User"
  },
  {
    "$type": "StringLiteralType",
    "value": "Application"
  },
  {
    "$type": "StringLiteralType",
    "value": "ManagedIdentity"
  },
  {
    "$type": "StringLiteralType",
    "value": "Key"
  },
  {
    "$type": "UnionType",
    "elements": [
      {
        "$ref": "#/57"
      },
      {
        "$ref": "#/58"
      },
      {
        "$ref": "#/59"
      },
      {
        "$ref": "#/60"
      },
      {
        "$ref": "#/2"
      }
    ]
  },
  {
    "$type": "ArrayType",
    "itemType": {
      "$ref": "#/37"
    }
  },
  {
    "$type": "StringLiteralType",
    "value": "enabled"
  },
  {
    "$type": "StringLiteralType",
    "value": "disabled"
  },
  {
    "$type": "UnionType",
    "elements": [
      {
        "$ref": "#/63"
      },
      {
        "$ref": "#/64"
      },
      {
        "$ref": "#/2"
      }
    ]
  },
  {
    "$type": "ObjectType",
    "name": "LocationsItem",
    "properties": {
      "locationName": {
        "type": {
          "$ref": "#/2"
        },
        "flags": 1,
        "description": "The location name."
      }
    }
  },
  {
    "$type": "ArrayType",
    "itemType": {
      "$ref": "#/66"
    }
  },
  {
    "$type": "ObjectType",
    "name": "TrackedResourceTags",
    "properties": {},
    "additionalProperties": {
      "$ref": "#/2"
    }
  },
  {
    "$type": "ResourceType",
    "name": "Microsoft.Maps/accounts@2024-01-01-preview",
    "body": {
      "$ref": "#/4"
    },
    "readableScopes": 8,
    "writableScopes": 8
  },
  {
    "$type": "StringLiteralType",
    "value": "Microsoft.Maps/accounts/creators"
  },
  {
    "$type": "StringLiteralType",
    "value": "2024-01-01-preview"
  },
  {
    "$type": "ObjectType",
    "name": "Microsoft.Maps/accounts/creators",
    "properties": {
      "id": {
        "type": {
          "$ref": "#/2"
        },
        "flags": 10,
        "description": "The resource id"
      },
      "name": {
        "type": {
          "$ref": "#/0"
        },
        "flags": 9,
        "description": "The resource name"
      },
      "type": {
        "type": {
          "$ref": "#/70"
        },
        "flags": 10,
        "description": "The resource type"
      },
      "apiVersion": {
        "type": {
          "$ref": "#/71"
        },
        "flags": 10,
        "description": "The resource api version"
      },
      "properties": {
        "type": {
          "$ref": "#/73"
        },
        "flags": 1,
        "description": "The Creator resource properties."
      },
      "tags": {
        "type": {
          "$ref": "#/76"
        },
        "flags": 0,
        "description": "Resource tags."
      },
      "location": {
        "type": {
          "$ref": "#/2"
        },
        "flags": 1,
        "description": "The geo-location where the resource lives"
      },
      "systemData": {
        "type": {
          "$ref": "#/51"
        },
        "flags": 2,
        "description": "Azure Resource Manager metadata containing createdBy and modifiedBy information."
      }
    }
  },
  {
    "$type": "ObjectType",
    "name": "CreatorProperties",
    "properties": {
      "provisioningState": {
        "type": {
          "$ref": "#/2"
        },
        "flags": 2,
        "description": "The state of the resource provisioning, terminal states: Succeeded, Failed, Canceled"
      },
      "storageUnits": {
        "type": {
          "$ref": "#/74"
        },
        "flags": 1,
        "description": "The storage units to be allocated. Integer values from 1 to 100, inclusive."
      },
      "totalStorageUnitSizeInBytes": {
        "type": {
          "$ref": "#/75"
        },
        "flags": 0,
        "description": "The total allocated storage unit size in bytes for the creator resource."
      },
      "consumedStorageUnitSizeInBytes": {
        "type": {
          "$ref": "#/75"
        },
        "flags": 0,
        "description": "The consumed storage unit size in bytes for the creator resource."
      }
    }
  },
  {
    "$type": "IntegerType",
    "minValue": 1,
    "maxValue": 100
  },
  {
    "$type": "IntegerType"
  },
  {
    "$type": "ObjectType",
    "name": "TrackedResourceTags",
    "properties": {},
    "additionalProperties": {
      "$ref": "#/2"
    }
  },
  {
    "$type": "ResourceType",
    "name": "Microsoft.Maps/accounts/creators@2024-01-01-preview",
    "body": {
      "$ref": "#/72"
    },
    "readableScopes": 8,
    "writableScopes": 8
  },
  {
    "$type": "StringLiteralType",
    "value": "Microsoft.Maps/accounts/privateEndpointConnections"
  },
  {
    "$type": "StringLiteralType",
    "value": "2024-01-01-preview"
  },
  {
    "$type": "ObjectType",
    "name": "Microsoft.Maps/accounts/privateEndpointConnections",
    "properties": {
      "id": {
        "type": {
          "$ref": "#/2"
        },
        "flags": 10,
        "description": "The resource id"
      },
      "name": {
        "type": {
          "$ref": "#/0"
        },
        "flags": 9,
        "description": "The resource name"
      },
      "type": {
        "type": {
          "$ref": "#/78"
        },
        "flags": 10,
        "description": "The resource type"
      },
      "apiVersion": {
        "type": {
          "$ref": "#/79"
        },
        "flags": 10,
        "description": "The resource api version"
      },
      "properties": {
        "type": {
          "$ref": "#/38"
        },
        "flags": 0,
        "description": "Resource properties."
      },
      "systemData": {
        "type": {
          "$ref": "#/51"
        },
        "flags": 2,
        "description": "Azure Resource Manager metadata containing createdBy and modifiedBy information."
      }
    }
  },
  {
    "$type": "ResourceType",
    "name": "Microsoft.Maps/accounts/privateEndpointConnections@2024-01-01-preview",
    "body": {
      "$ref": "#/80"
    },
    "readableScopes": 8,
    "writableScopes": 8
  },
  {
    "$type": "StringType",
    "pattern": "^.*$"
  },
  {
    "$type": "StringLiteralType",
    "value": "Microsoft.Maps/accounts/privateLinkResources"
  },
  {
    "$type": "StringLiteralType",
    "value": "2024-01-01-preview"
  },
  {
    "$type": "ObjectType",
    "name": "Microsoft.Maps/accounts/privateLinkResources",
    "properties": {
      "id": {
        "type": {
          "$ref": "#/2"
        },
        "flags": 10,
        "description": "The resource id"
      },
      "name": {
        "type": {
          "$ref": "#/82"
        },
        "flags": 9,
        "description": "The resource name"
      },
      "type": {
        "type": {
          "$ref": "#/83"
        },
        "flags": 10,
        "description": "The resource type"
      },
      "apiVersion": {
        "type": {
          "$ref": "#/84"
        },
        "flags": 10,
        "description": "The resource api version"
      },
      "properties": {
        "type": {
          "$ref": "#/86"
        },
        "flags": 2,
        "description": "Resource properties."
      },
      "systemData": {
        "type": {
          "$ref": "#/51"
        },
        "flags": 2,
        "description": "Azure Resource Manager metadata containing createdBy and modifiedBy information."
      }
    }
  },
  {
    "$type": "ObjectType",
    "name": "PrivateLinkResourceProperties",
    "properties": {
      "groupId": {
        "type": {
          "$ref": "#/2"
        },
        "flags": 2,
        "description": "The private link resource group id."
      },
      "requiredMembers": {
        "type": {
          "$ref": "#/87"
        },
        "flags": 2,
        "description": "The private link resource required member names."
      },
      "requiredZoneNames": {
        "type": {
          "$ref": "#/88"
        },
        "flags": 0,
        "description": "The private link resource private link DNS zone name."
      }
    }
  },
  {
    "$type": "ArrayType",
    "itemType": {
      "$ref": "#/2"
    }
  },
  {
    "$type": "ArrayType",
    "itemType": {
      "$ref": "#/2"
    }
  },
  {
    "$type": "ResourceType",
    "name": "Microsoft.Maps/accounts/privateLinkResources@2024-01-01-preview",
    "body": {
      "$ref": "#/85"
    },
    "readableScopes": 8,
    "writableScopes": 0
  },
  {
    "$type": "ObjectType",
    "name": "AccountSasParameters",
    "properties": {
      "signingKey": {
        "type": {
          "$ref": "#/94"
        },
        "flags": 1,
        "description": "The Maps account key to use for signing. Picking `primaryKey` or `secondaryKey` will use the Maps account Shared Keys, and using `managedIdentity` will use the auto-renewed private key to sign the SAS."
      },
      "principalId": {
        "type": {
          "$ref": "#/2"
        },
        "flags": 1,
        "description": "The principal Id also known as the object Id of a User Assigned Managed Identity currently assigned to the Maps Account. To assign a Managed Identity of the account, use operation Create or Update an assign a User Assigned Identity resource Id."
      },
      "regions": {
        "type": {
          "$ref": "#/95"
        },
        "flags": 0,
        "description": "Optional, allows control of which region locations are permitted access to Azure Maps REST APIs with the SAS token. Example: \"eastus\", \"westus2\". Omitting this parameter will allow all region locations to be accessible."
      },
      "maxRatePerSecond": {
        "type": {
          "$ref": "#/96"
        },
        "flags": 1,
        "description": "Required parameter which represents the desired maximum request per second to allowed for the given SAS token. This does not guarantee perfect accuracy in measurements but provides application safe guards of abuse with eventual enforcement."
      },
      "start": {
        "type": {
          "$ref": "#/2"
        },
        "flags": 1,
        "description": "The date time offset of when the token validity begins. For example \"2017-05-24T10:42:03.1567373Z\". Maximum duration allowed is 24 hours between `start` and `expiry`."
      },
      "expiry": {
        "type": {
          "$ref": "#/2"
        },
        "flags": 1,
        "description": "The date time offset of when the token validity expires. For example \"2017-05-24T10:42:03.1567373Z\". Maximum duration allowed is 24 hours between `start` and `expiry`."
      }
    }
  },
  {
    "$type": "StringLiteralType",
    "value": "primaryKey"
  },
  {
    "$type": "StringLiteralType",
    "value": "secondaryKey"
  },
  {
    "$type": "StringLiteralType",
    "value": "managedIdentity"
  },
  {
    "$type": "UnionType",
    "elements": [
      {
        "$ref": "#/91"
      },
      {
        "$ref": "#/92"
      },
      {
        "$ref": "#/93"
      },
      {
        "$ref": "#/2"
      }
    ]
  },
  {
    "$type": "ArrayType",
    "itemType": {
      "$ref": "#/2"
    }
  },
  {
    "$type": "IntegerType",
    "minValue": 1,
    "maxValue": 500
  },
  {
    "$type": "ObjectType",
    "name": "MapsAccountSasToken",
    "properties": {
      "accountSasToken": {
        "type": {
          "$ref": "#/2"
        },
        "flags": 2,
        "description": "The shared access signature access token."
      }
    }
  },
  {
    "$type": "ResourceFunctionType",
    "name": "listSas",
    "resourceType": "Microsoft.Maps/accounts",
    "apiVersion": "2024-01-01-preview",
    "output": {
      "$ref": "#/97"
    },
    "input": {
      "$ref": "#/90"
    }
  },
  {
    "$type": "ObjectType",
    "name": "MapsAccountKeys",
    "properties": {
      "primaryKeyLastUpdated": {
        "type": {
          "$ref": "#/2"
        },
        "flags": 2,
        "description": "The last updated date and time of the primary key."
      },
      "primaryKey": {
        "type": {
          "$ref": "#/2"
        },
        "flags": 2,
        "description": "The primary key for accessing the Maps REST APIs."
      },
      "secondaryKey": {
        "type": {
          "$ref": "#/2"
        },
        "flags": 2,
        "description": "The secondary key for accessing the Maps REST APIs."
      },
      "secondaryKeyLastUpdated": {
        "type": {
          "$ref": "#/2"
        },
        "flags": 2,
        "description": "The last updated date and time of the secondary key."
      }
    }
  },
  {
    "$type": "ResourceFunctionType",
    "name": "listKeys",
    "resourceType": "Microsoft.Maps/accounts",
    "apiVersion": "2024-01-01-preview",
    "output": {
      "$ref": "#/99"
    }
  },
  {
    "$type": "ObjectType",
    "name": "MapsKeySpecification",
    "properties": {
      "keyType": {
        "type": {
          "$ref": "#/104"
        },
        "flags": 1,
        "description": "Whether the operation refers to the primary or secondary key."
      }
    }
  },
  {
    "$type": "StringLiteralType",
    "value": "primary"
  },
  {
    "$type": "StringLiteralType",
    "value": "secondary"
  },
  {
    "$type": "UnionType",
    "elements": [
      {
        "$ref": "#/102"
      },
      {
        "$ref": "#/103"
      },
      {
        "$ref": "#/2"
      }
    ]
  },
  {
    "$type": "ResourceFunctionType",
    "name": "regenerateKey",
    "resourceType": "Microsoft.Maps/accounts",
    "apiVersion": "2024-01-01-preview",
    "output": {
      "$ref": "#/99"
    },
    "input": {
      "$ref": "#/101"
    }
  }
]