[{"1":{"Kind":1}},{"1":{"Kind":2}},{"1":{"Kind":3}},{"1":{"Kind":4}},{"1":{"Kind":5}},{"1":{"Kind":6}},{"1":{"Kind":7}},{"1":{"Kind":8}},{"2":{"Name":"ComponentPolicyStatesQueryResults","Properties":{"@odata.context":{"Type":4,"Flags":0,"Description":"OData context string; used by OData clients to resolve type information based on metadata."},"@odata.count":{"Type":3,"Flags":0,"Description":"OData entity count; represents the number of policy state records returned."},"value":{"Type":14,"Flags":0,"Description":"Query results."}}}},{"2":{"Name":"ComponentPolicyState","Properties":{"@odata.id":{"Type":4,"Flags":2,"Description":"OData entity ID; always set to null since component policy state records do not have an entity ID."},"@odata.context":{"Type":4,"Flags":2,"Description":"OData context string; used by OData clients to resolve type information based on metadata."},"timestamp":{"Type":4,"Flags":2,"Description":"Timestamp for the component policy state record."},"componentId":{"Type":4,"Flags":2,"Description":"Component Id."},"componentType":{"Type":4,"Flags":2,"Description":"Component type."},"componentName":{"Type":4,"Flags":2,"Description":"Component name."},"resourceId":{"Type":4,"Flags":2,"Description":"Resource ID."},"policyAssignmentId":{"Type":4,"Flags":2,"Description":"Policy assignment ID."},"policyDefinitionId":{"Type":4,"Flags":2,"Description":"Policy definition ID."},"subscriptionId":{"Type":4,"Flags":2,"Description":"Subscription ID."},"resourceType":{"Type":4,"Flags":2,"Description":"Resource type."},"resourceLocation":{"Type":4,"Flags":2,"Description":"Resource location."},"resourceGroup":{"Type":4,"Flags":2,"Description":"Resource group name."},"policyAssignmentName":{"Type":4,"Flags":2,"Description":"Policy assignment name."},"policyAssignmentOwner":{"Type":4,"Flags":2,"Description":"Policy assignment owner."},"policyAssignmentParameters":{"Type":4,"Flags":2,"Description":"Policy assignment parameters."},"policyAssignmentScope":{"Type":4,"Flags":2,"Description":"Policy assignment scope."},"policyDefinitionName":{"Type":4,"Flags":2,"Description":"Policy definition name."},"policyDefinitionAction":{"Type":4,"Flags":2,"Description":"Policy definition action, i.e. effect."},"policyDefinitionCategory":{"Type":4,"Flags":2,"Description":"Policy definition category."},"policySetDefinitionId":{"Type":4,"Flags":2,"Description":"Policy set definition ID, if the policy assignment is for a policy set."},"policySetDefinitionName":{"Type":4,"Flags":2,"Description":"Policy set definition name, if the policy assignment is for a policy set."},"policySetDefinitionOwner":{"Type":4,"Flags":2,"Description":"Policy set definition owner, if the policy assignment is for a policy set."},"policySetDefinitionCategory":{"Type":4,"Flags":2,"Description":"Policy set definition category, if the policy assignment is for a policy set."},"policySetDefinitionParameters":{"Type":4,"Flags":2,"Description":"Policy set definition parameters, if the policy assignment is for a policy set."},"policyDefinitionReferenceId":{"Type":4,"Flags":2,"Description":"Reference ID for the policy definition inside the policy set, if the policy assignment is for a policy set."},"complianceState":{"Type":4,"Flags":2,"Description":"Compliance state of the resource."},"policyEvaluationDetails":{"Type":10,"Flags":0,"Description":"Policy evaluation details. This is only included in the response if the request contains $expand=PolicyEvaluationDetails."},"policyDefinitionGroupNames":{"Type":13,"Flags":2,"Description":"Policy definition group names."},"policyDefinitionVersion":{"Type":4,"Flags":2,"Description":"Evaluated policy definition version."},"policySetDefinitionVersion":{"Type":4,"Flags":2,"Description":"Evaluated policy set definition version."},"policyAssignmentVersion":{"Type":4,"Flags":2,"Description":"Evaluated policy assignment version."}},"AdditionalProperties":0}},{"2":{"Name":"ComponentPolicyEvaluationDetails","Properties":{"evaluatedExpressions":{"Type":12,"Flags":2,"Description":"Details of the evaluated expressions."},"reason":{"Type":4,"Flags":0,"Description":"Additional textual reason for the evaluation outcome."}}}},{"2":{"Name":"ComponentExpressionEvaluationDetails","Properties":{"result":{"Type":4,"Flags":0,"Description":"Evaluation result."},"expression":{"Type":4,"Flags":2,"Description":"Expression evaluated."},"expressionKind":{"Type":4,"Flags":2,"Description":"The kind of expression that was evaluated."},"path":{"Type":4,"Flags":2,"Description":"Property path if the expression is a field or an alias."},"expressionValue":{"Type":0,"Flags":2,"Description":"Value of the expression."},"targetValue":{"Type":0,"Flags":2,"Description":"Target value to be compared with the expression value."},"operator":{"Type":4,"Flags":2,"Description":"Operator to compare the expression value and the target value."}}}},{"3":{"ItemType":11}},{"3":{"ItemType":4}},{"3":{"ItemType":9}},{"8":{"Name":"queryResults","ResourceType":"Microsoft.PolicyInsights/componentPolicyStates","ApiVersion":"2022-04-01","Output":8}}]